{"index":"scarecrow","name":"Scarecrow","size":"Medium","type":"construct,","subtype":null,"alignment":" chaotic evil","armor_class":11,"hit_points":36,"hit_dice":"8d8","speed":{"walk":"30 ft."},"strength":11,"dexterity":13,"constitution":11,"intelligence":10,"wisdom":10,"charisma":13,"spells":[],"spell_slots":{},"url":"https://www.dndbeyond.com/monsters/scarecrow","damage_vulnerabilities":["Fire"],"damage_resistances":["Bludgeoning","Piercing","and Slashing from Nonmagical Attacks"],"damage_immunities":["Poison"],"condition_immunities":["Charmed","Exhaustion","Frightened","Paralyzed","Poisoned","Unconscious"],"senses":"Darkvision 60 ft. | Passive Perception 10","languages":"understands the languages of its creator but can’t speak","challenge_rating":"1","xp":200,"special_abilities":[{"name":"False Appearance.","desc":" While the scarecrow remains motionless, it is indistinguishable from an ordinary, inanimate scarecrow."}],"actions":[{"name":"Multiattack.","desc":" The scarecrow makes two claw attacks."},{"name":"Claw.","desc":" Melee Weapon Attack: +3 to hit, reach 5 ft., one target. Hit: 6 (2d4 + 1) slashing damage. If the target is a creature, it must succeed on a DC 11 Wisdom saving throw or be frightened until the end of the scarecrow’s next turn."},{"name":"Terrifying Glare","desc":". The scarecrow targets one creature it can see within 30 feet of it. If the target can see the scarecrow, the target must succeed on a DC 11 Wisdom saving throw or be magically frightened until the end of the scarecrow’s next turn. The frightened target is paralyzed."}]}